{
  "info": {
    "name": "City Council, District 5 - Berkeley",
    "date": "2024-11-05",
    "dataFormat": "nist_sp_1500",
    "tabulationOptions": {
      "eager": true,
      "nycStyle": false
    },
    "jurisdictionPath": "us/ca/alameda",
    "electionPath": "2024/11",
    "office": "berkeley-council-d5",
    "officeName": "City Council, District 5 - Berkeley",
    "jurisdictionName": "Alameda County",
    "electionName": "November 5, 2024 General Election",
    "loaderParams": {
      "contest": "90",
      "cvr": "nov-05-general",
      "dropUnqualifiedWriteIn": "true"
    },
    "website": null
  },
  "ballotCount": 10258,
  "candidates": [
    {
      "name": "Nilang Gor",
      "candidate_type": "Regular"
    },
    {
      "name": "Todd Andrew",
      "candidate_type": "Regular"
    },
    {
      "name": "Shoshana O'Keefe",
      "candidate_type": "Regular"
    }
  ],
  "rounds": [
    {
      "allocations": [
        {
          "allocatee": 2,
          "votes": 5830
        },
        {
          "allocatee": 1,
          "votes": 1733
        },
        {
          "allocatee": 0,
          "votes": 1085
        },
        {
          "allocatee": "X",
          "votes": 1610
        }
      ],
      "undervote": 1587,
      "overvote": 23,
      "continuingBallots": 8648,
      "transfers": []
    },
    {
      "allocations": [
        {
          "allocatee": 2,
          "votes": 6267
        },
        {
          "allocatee": 1,
          "votes": 1995
        },
        {
          "allocatee": "X",
          "votes": 1996
        }
      ],
      "undervote": 1972,
      "overvote": 24,
      "continuingBallots": 8262,
      "transfers": [
        {
          "from": 0,
          "to": 2,
          "count": 437
        },
        {
          "from": 0,
          "to": 1,
          "count": 262
        },
        {
          "from": 0,
          "to": "X",
          "count": 386
        }
      ]
    }
  ],
  "winner": 2,
  "condorcet": 2,
  "numCandidates": 3,
  "totalVotes": [
    {
      "candidate": 0,
      "firstRoundVotes": 1085,
      "transferVotes": 0,
      "roundEliminated": 1
    },
    {
      "candidate": 1,
      "firstRoundVotes": 1733,
      "transferVotes": 262,
      "roundEliminated": null
    },
    {
      "candidate": 2,
      "firstRoundVotes": 5830,
      "transferVotes": 437,
      "roundEliminated": null
    }
  ],
  "pairwisePreferences": {
    "rows": [
      0,
      1,
      2
    ],
    "cols": [
      0,
      1,
      2
    ],
    "entries": [
      [
        null,
        {
          "frac": 0.3253324,
          "numerator": 1884,
          "denominator": 5791
        },
        {
          "frac": 0.16760616,
          "numerator": 1338,
          "denominator": 7983
        }
      ],
      [
        {
          "frac": 0.6746676,
          "numerator": 3907,
          "denominator": 5791
        },
        null,
        {
          "frac": 0.24146695,
          "numerator": 1995,
          "denominator": 8262
        }
      ],
      [
        {
          "frac": 0.8323938,
          "numerator": 6645,
          "denominator": 7983
        },
        {
          "frac": 0.75853306,
          "numerator": 6267,
          "denominator": 8262
        },
        null
      ]
    ]
  },
  "firstAlternate": {
    "rows": [
      0,
      1,
      2
    ],
    "cols": [
      0,
      1,
      2,
      "X"
    ],
    "entries": [
      [
        null,
        {
          "frac": 0.24147466,
          "numerator": 262,
          "denominator": 1085
        },
        {
          "frac": 0.40276498,
          "numerator": 437,
          "denominator": 1085
        },
        {
          "frac": 0.35576037,
          "numerator": 386,
          "denominator": 1085
        }
      ],
      [
        {
          "frac": 0.14598961,
          "numerator": 253,
          "denominator": 1733
        },
        null,
        {
          "frac": 0.47028273,
          "numerator": 815,
          "denominator": 1733
        },
        {
          "frac": 0.38372764,
          "numerator": 665,
          "denominator": 1733
        }
      ],
      [
        {
          "frac": 0.13704975,
          "numerator": 799,
          "denominator": 5830
        },
        {
          "frac": 0.3728988,
          "numerator": 2174,
          "denominator": 5830
        },
        null,
        {
          "frac": 0.49005145,
          "numerator": 2857,
          "denominator": 5830
        }
      ]
    ]
  },
  "firstFinal": {
    "rows": [
      0
    ],
    "cols": [
      1,
      2,
      "X"
    ],
    "entries": [
      [
        {
          "frac": 0.24147466,
          "numerator": 262,
          "denominator": 1085
        },
        {
          "frac": 0.40276498,
          "numerator": 437,
          "denominator": 1085
        },
        {
          "frac": 0.35576037,
          "numerator": 386,
          "denominator": 1085
        }
      ]
    ]
  },
  "rankingDistribution": {
    "overallDistribution": {
      "1": 3908,
      "2": 2266,
      "3": 2474
    },
    "candidateDistributions": {
      "0": {
        "1": 386,
        "2": 245,
        "3": 454
      },
      "1": {
        "1": 665,
        "2": 616,
        "3": 452
      },
      "2": {
        "1": 2857,
        "2": 1405,
        "3": 1568
      }
    },
    "totalBallots": 8648,
    "candidateTotals": {
      "0": 1085,
      "1": 1733,
      "2": 5830
    }
  },
  "smithSet": [
    2
  ]
}